goux/__init__.py
goux/met.py
pymal_basic/__init__.py
pymal_basic/math.py
goux-0.0.1.dist-info/LICENSE
goux-0.0.1.dist-info/METADATA
goux-0.0.1.dist-info/WHEEL
goux-0.0.1.dist-info/top_level.txt
goux-0.0.1.dist-info/RECORD
